MANIFEST.in
README
setup.py
TopZooTools/__init__.py
TopZooTools/converter.py
TopZooTools/geocoder.py
TopZooTools/geoplot.py
TopZooTools/rocketfuel2zoo.py
TopZooTools/yed2zoo.py
TopZooTools/zoostats.py
topzootools.egg-info/PKG-INFO
topzootools.egg-info/SOURCES.txt
topzootools.egg-info/dependency_links.txt
topzootools.egg-info/entry_points.txt
topzootools.egg-info/requires.txt
topzootools.egg-info/top_level.txt